bottle_auth
