Metadata-Version: 1.1
Name: bottle-auth
Version: 0.3.3
Summary: Bootle authentication, for Personal, Google, Twitter and facebook.
Home-page: https://github.com/avelino/bottle-auth
Author: Thiago Avelino
Author-email: thiago@avelino.xxx
License: UNKNOWN
Platform: UNKNOWN
Classifier: Environment :: Web Environment
Classifier: Environment :: Plugins
Classifier: Framework :: Bottle
Classifier: Intended Audience :: Developers
Classifier: License :: OSI Approved :: MIT License
Classifier: Operating System :: OS Independent
Classifier: Programming Language :: Python
Classifier: Topic :: Internet :: WWW/HTTP :: Dynamic Content
Classifier: Topic :: Software Development :: Libraries :: Python Modules
